ind_equity_derivatives/__init__.py
ind_equity_derivatives/nse_data.py
smart_algo_trading-0.0.1.dist-info/LICENSE
smart_algo_trading-0.0.1.dist-info/METADATA
smart_algo_trading-0.0.1.dist-info/WHEEL
smart_algo_trading-0.0.1.dist-info/top_level.txt
smart_algo_trading-0.0.1.dist-info/RECORD
