Metadata-Version: 2.1
Name: smart-algo-trading
Version: 0.0.1
Summary: A python package to provide simple and smart Algo Trading module to build robust and scalable application
Home-page: https://github.com/easycloudapi/algo_trading
Author: Indranil Pal
Author-email: info.easycloudapi@gmail.com
Project-URL: Bug Tracker, https://github.com/easycloudapi/algo_trading/issues
Project-URL: repository, https://github.com/easycloudapi/algo_trading
Keywords: Algo-Trading,algo,trading,python
Classifier: Programming Language :: Python :: 3
Classifier: License :: OSI Approved :: MIT License
Classifier: Operating System :: OS Independent
Requires-Python: >=3.10.5
License-File: LICENSE
Requires-Dist: requests ==2.31.0
